README.md
setup.py
freshdesk_api_client/__init__.py
freshdesk_api_client/client.py
freshdesk_api_client/interfaces.py
freshdesk_api_client/resources.py
freshdesk_api_client/result.py
freshdesk_api_client/utils.py
freshdesk_api_client.egg-info/PKG-INFO
freshdesk_api_client.egg-info/SOURCES.txt
freshdesk_api_client.egg-info/dependency_links.txt
freshdesk_api_client.egg-info/top_level.txt